odoo9_addon_web_timeline-9.0.1.0.0-py2.7-nspkg.pth
odoo9_addon_web_timeline-9.0.1.0.0.dist-info/DESCRIPTION.rst
odoo9_addon_web_timeline-9.0.1.0.0.dist-info/METADATA
odoo9_addon_web_timeline-9.0.1.0.0.dist-info/RECORD
odoo9_addon_web_timeline-9.0.1.0.0.dist-info/WHEEL
odoo9_addon_web_timeline-9.0.1.0.0.dist-info/metadata.json
odoo9_addon_web_timeline-9.0.1.0.0.dist-info/namespace_packages.txt
odoo9_addon_web_timeline-9.0.1.0.0.dist-info/top_level.txt
odoo_addons/web_timeline/README.rst
odoo_addons/web_timeline/__init__.py
odoo_addons/web_timeline/__openerp__.py
odoo_addons/web_timeline/models/__init__.py
odoo_addons/web_timeline/models/ir_view.py
odoo_addons/web_timeline/static/description/icon.png
odoo_addons/web_timeline/static/lib/vis/vis.css
odoo_addons/web_timeline/static/lib/vis/vis.js
odoo_addons/web_timeline/static/lib/vis/vis.map
odoo_addons/web_timeline/static/lib/vis/vis.min.css
odoo_addons/web_timeline/static/lib/vis/vis.min.js
odoo_addons/web_timeline/static/lib/vis/img/network/acceptDeleteIcon.png
odoo_addons/web_timeline/static/lib/vis/img/network/addNodeIcon.png
odoo_addons/web_timeline/static/lib/vis/img/network/backIcon.png
odoo_addons/web_timeline/static/lib/vis/img/network/connectIcon.png
odoo_addons/web_timeline/static/lib/vis/img/network/cross.png
odoo_addons/web_timeline/static/lib/vis/img/network/cross2.png
odoo_addons/web_timeline/static/lib/vis/img/network/deleteIcon.png
odoo_addons/web_timeline/static/lib/vis/img/network/downArrow.png
odoo_addons/web_timeline/static/lib/vis/img/network/editIcon.png
odoo_addons/web_timeline/static/lib/vis/img/network/leftArrow.png
odoo_addons/web_timeline/static/lib/vis/img/network/minus.png
odoo_addons/web_timeline/static/lib/vis/img/network/plus.png
odoo_addons/web_timeline/static/lib/vis/img/network/rightArrow.png
odoo_addons/web_timeline/static/lib/vis/img/network/upArrow.png
odoo_addons/web_timeline/static/lib/vis/img/network/zoomExtends.png
odoo_addons/web_timeline/static/lib/vis/img/timeline/delete.png
odoo_addons/web_timeline/static/src/css/web_timeline.css
odoo_addons/web_timeline/static/src/js/web_timeline.js
odoo_addons/web_timeline/static/src/xml/web_timeline.xml
odoo_addons/web_timeline/views/web_timeline.xml
