Metadata-Version: 2.0
Name: odoo9-addon-web-timeline
Version: 9.0.1.0.0
Summary: Interactive visualization chart to show events in time
Home-page: http://acsone.eu
Author: ACSONE SA/NV,Tecnativa,Odoo Community Association (OCA)
Author-email: support@odoo-community.org
License: UNKNOWN
Platform: UNKNOWN
Classifier: Programming Language :: Python :: 2.7
Classifier: Framework :: Odoo
Requires-Dist: odoo (<9.1a,>=9.0a)
